rslattice-0.1.1.dist-info/METADATA
rslattice-0.1.1.dist-info/WHEEL
rslattice-0.1.1.dist-info/licenses/LICENSE.txt
rslattice/__init__.py
rslattice/rslattice.abi3.so
rslattice-0.1.1.dist-info/RECORD
