Metadata-Version: 2.4
Name: rslattice
Version: 0.1.1
Classifier: Programming Language :: Rust
Classifier: Programming Language :: Python :: Implementation :: CPython
Classifier: Programming Language :: Python :: Implementation :: PyPy
Requires-Dist: numpy <2.0
Requires-Dist: pytest ; extra == 'tests'
Provides-Extra: tests
License-File: LICENSE.txt
Summary: Python module for doing calculations on integer lattices.
Home-Page: https://github.com/Sin-tel/rslattice
Author: Sintel
License: MIT
Requires-Python: >=3.8
Project-URL: Source Code, https://github.com/Sin-tel/rslattice
